{
  "type": "forge:conditional",
  "recipes": [
    {
      "conditions": [
        {
          "module_name": "te",
          "type": "tieredmagnets:module_enabled"
        }
      ],
      "recipe": {
        "type": "minecraft:crafting_shaped",
        "pattern": [
          " A ",
          "BMB",
          " A "
        ],
        "key": {
          "M": {
            "item": "tieredmagnets:magnet_energy_reinforced"
          },
          "A": {
            "item": "minecraft:redstone"
          },
          "B": {
            "item": "minecraft:gold_ingot"
          }
        },
        "result": {
          "item": "tieredmagnets:magnet_energy_signalum"
        }
      }
    }
  ]
}